podaac/hitide_backfill_tool/__init__.py
podaac/hitide_backfill_tool/args.py
podaac/hitide_backfill_tool/cli.py
podaac/hitide_backfill_tool/cmr/__init__.py
podaac/hitide_backfill_tool/cmr/cmr_granule.py
podaac/hitide_backfill_tool/cmr/helpers.py
podaac/hitide_backfill_tool/cmr/search.py
podaac/hitide_backfill_tool/cnm_message_writer.py
podaac/hitide_backfill_tool/config.py
podaac/hitide_backfill_tool/config_creator.py
podaac/hitide_backfill_tool/default_message_config.json
podaac/hitide_backfill_tool/dmrpp_utils.py
podaac/hitide_backfill_tool/failed_workflow.py
podaac/hitide_backfill_tool/file_util.py
podaac/hitide_backfill_tool/memory_profiler.py
podaac/hitide_backfill_tool/regression.py
podaac/hitide_backfill_tool/replay.py
podaac/hitide_backfill_tool/s3_reader.py
podaac/hitide_backfill_tool/sns_message_sender.py
podaac_hitide_backfill_tool-0.9.0.dist-info/LICENSE
podaac_hitide_backfill_tool-0.9.0.dist-info/METADATA
podaac_hitide_backfill_tool-0.9.0.dist-info/WHEEL
podaac_hitide_backfill_tool-0.9.0.dist-info/entry_points.txt
podaac_hitide_backfill_tool-0.9.0.dist-info/RECORD
