Metadata-Version: 2.1
Name: podaac-hitide-backfill-tool
Version: 0.9.0
Summary: Backfill footprints and images for HiTIDE collections
Home-page: https://github.com/podaac/hitide-backfill-tool
License: Apache-2.0
Author: PO.DAAC
Author-email: podaac@jpl.nasa.gov
Requires-Python: >=3.10,<4.0
Classifier: License :: OSI Approved :: Apache Software License
Classifier: Programming Language :: Python :: 3
Classifier: Programming Language :: Python :: 3.10
Classifier: Programming Language :: Python :: 3.11
Classifier: Programming Language :: Python :: 3.12
Classifier: Topic :: Software Development :: Libraries :: Python Modules
Requires-Dist: boto3 (>=1.35.0,<2.0.0)
Requires-Dist: fuzzywuzzy (>=0.18.0,<0.19.0)
Requires-Dist: python-Levenshtein (>=0.25.0,<0.26.0)
Requires-Dist: pyyaml (>=6.0,<7.0)
Requires-Dist: requests (>=2.27.1,<3.0.0)
Project-URL: Repository, https://github.com/podaac/hitide-backfill-tool
